CONTRIBUTORS.txt
MANIFEST.in
README.txt
setup.py
collective/__init__.py
collective.portlet.rssjs.egg-info/PKG-INFO
collective.portlet.rssjs.egg-info/SOURCES.txt
collective.portlet.rssjs.egg-info/dependency_links.txt
collective.portlet.rssjs.egg-info/entry_points.txt
collective.portlet.rssjs.egg-info/namespace_packages.txt
collective.portlet.rssjs.egg-info/not-zip-safe
collective.portlet.rssjs.egg-info/requires.txt
collective.portlet.rssjs.egg-info/top_level.txt
collective/portlet/__init__.py
collective/portlet/rssjs/__init__.py
collective/portlet/rssjs/configure.zcml
collective/portlet/rssjs/rssjsportlet.pt
collective/portlet/rssjs/rssjsportlet.py
collective/portlet/rssjs/version.txt
collective/portlet/rssjs/browser/__init__.py
collective/portlet/rssjs/browser/configure.zcml
collective/portlet/rssjs/browser/load.rss.portlets.js
collective/portlet/rssjs/profiles/default/jsregistry.xml
collective/portlet/rssjs/profiles/default/metadata.xml
collective/portlet/rssjs/profiles/default/portlets.xml
collective/portlet/rssjs/tests/__init__.py
collective/portlet/rssjs/tests/base.py
collective/portlet/rssjs/tests/test_portlet.py
docs/.HISTORY.txt.swp
docs/HISTORY.txt
docs/INSTALL.txt
docs/LICENSE.GPL
docs/LICENSE.txt