Metadata-Version: 1.0
Name: collective.portlet.rssjs
Version: 0.2
Summary: Rss Portlet using javascript to get, parse and render an RSS feed on the client
Home-page: http://svn.plone.org/svn/collective/collective.portlet.rssjs/
Author: Hans-Peter Locher
Author-email: hans-peter.locher@inquant.de
License: GPL
Platform: UNKNOWN
Classifier: Framework :: Plone
Classifier: Programming Language :: Python
